couchbase_connection/__init__.py
couchbase_connection/connection.py
couchbase_connection-0.0.4.dist-info/METADATA
couchbase_connection-0.0.4.dist-info/WHEEL
couchbase_connection-0.0.4.dist-info/top_level.txt
couchbase_connection-0.0.4.dist-info/RECORD
