Metadata-Version: 2.2
Name: couchbase_connection
Version: 0.0.4
Summary: A Couchbase connector for Streamlit
Download-URL: https://github.com/VirajAgarwal1/couchbase_connection/archive/refs/tags/0.0.3.tar.gz
Author: Viraj Agarwal
Author-email: virajagarwal15@gmail.com
Keywords: couchbase,streamlit,connector,couchbase-streamlit-connector,python
Classifier: Development Status :: 4 - Beta
Classifier: Intended Audience :: Developers
Classifier: Topic :: Database
Classifier: Programming Language :: Python :: 3
Classifier: Programming Language :: Python :: 3.7
Classifier: Programming Language :: Python :: 3.8
Classifier: Programming Language :: Python :: 3.9
Classifier: Programming Language :: Python :: 3.10
Classifier: Programming Language :: Python :: 3.13
Classifier: Operating System :: OS Independent
Requires-Dist: couchbase
Requires-Dist: streamlit
Dynamic: author
Dynamic: author-email
Dynamic: classifier
Dynamic: description
Dynamic: download-url
Dynamic: keywords
Dynamic: requires-dist
Dynamic: summary
